{"path": "/Users/tranquangdang21/Projects/fast_file_search/crates/ffs-symbol/src/lib.rs", "mode": "raw", "body": "//! Symbol indexing and AST-driven outline extraction for ffs.\n//!\n//! Three primary services exposed by this crate:\n//!\n//! * [`bloom`] \u2014 a per-file probabilistic membership filter for fast\n//!   \"does file X contain symbol Y?\" pre-checks before tree-sitter parsing.\n//! * [`symbol_index`] \u2014 a concurrent map from `symbol_name -> Vec<Location>`\n//!   built by walking files in parallel with `ignore` + `rayon`.\n//! * [`outline`] \u2014 tree-sitter driven structural extraction (functions,\n//!   classes, traits, modules, \u2026) usable for outline view modes.\n//!\n//! All public types live in [`types`]. Language detection and tree-sitter\n//! grammar lookup live in [`lang`] and [`treesitter`].\n\npub mod artifact;\npub mod batch;\npub mod bloom;\npub mod detection;\npub mod lang;\npub mod outline;\npub mod outline_cache;\npub mod symbol_index;\npub mod treesitter;\npub mod types;\nmod verse_spans;\n\npub use bloom::{BloomFilter, BloomFilterCache};\npub use lang::{detect_file_type, package_root};\npub use outline::{get_outline_entries, outline_language};\npub use outline_cache::OutlineCache;\npub use symbol_index::{SymbolIndex, SymbolIndexSnapshot, SymbolLocation};\npub use treesitter::{\n    definition_weight, extract_definition_name, extract_impl_trait, extract_impl_type,\n    extract_implemented_interfaces, DEFINITION_KINDS,\n};\npub use types::{\n    estimate_tokens, is_test_file, truncate_str, FileType, Lang, Match, OutlineEntry, OutlineKind,\n    QueryType, SearchResult, ViewMode,\n};\n", "kept_bytes": 1302, "footer_bytes": 0}