{"path": "/Users/tranquangdang21/Projects/fast_file_search/crates/ffs-cli/src/commands/callees_resolve.rs", "mode": "raw", "body": "use std::collections::BTreeSet;\n\nuse tree_sitter::{Node, Parser};\n\nuse ffs_symbol::outline_language;\nuse ffs_symbol::types::Lang;\n\n// Returns the set of identifier names referenced as call-targets inside lines\n// `[start_line, end_line]` of `content` parsed under `lang`.\n//\n// \"Call target\" covers the AST nodes most languages use for a call expression,\n// e.g. `call_expression`, `call`, `method_invocation`, `invocation_expression`,\n// `member_call_expression`, plus `macro_invocation` for Rust. The callee\n// identifier is taken from the conventional field (`function`, `name`,\n// `callee`) and reduced to its rightmost name segment, so `mod::Foo::bar()`\n// and `obj.bar()` both yield `bar` \u2014 the form the symbol index keys on.\npub fn collect_callees(\n    content: &str,\n    lang: Lang,\n    start_line: u32,\n    end_line: u32,\n) -> Option<BTreeSet<String>> {\n    let language = outline_language(lang)?;\n    let mut parser = Parser::new();\n    parser.set_language(&language).ok()?;\n    let tree = parser.parse(content, None)?;\n    let source = content.as_bytes();\n\n    let mut out: BTreeSet<String> = BTreeSet::new();\n    walk(tree.root_node(), source, start_line, end_line, &mut out);\n    Some(out)\n}\n\nfn walk(node: Node, src: &[u8], start: u32, end: u32, out: &mut BTreeSet<String>) {\n    let row = node.start_position().row as u32 + 1;\n    if row > end {\n        return;\n    }\n\n    if node_is_call(node) && row >= start {\n        if let Some(name) = extract_callee_name(node, src) {\n            out.insert(name);\n        }\n    }\n\n    // Verse: `Comp.BindPlot(Plot)` often parses as sibling `member_access` +\n    // `parenthesized_expression` instead of a single `call_expression`.\n    if node.kind() == \"member_access\" && row >= start {\n        if let Some(next) = node.next_named_sibling() {\n            if next.kind() == \"parenthesized_expression\" {\n                if let Some(member) = node.child_by_field_name(\"member\") {\n                    if let Some(name) = rightmost_name(member, src)", "kept_bytes": 601, "footer_bytes": 0, "view": "signatures"}